play_audio_with_vlc/LICENSE
play_audio_with_vlc/README.MD
play_audio_with_vlc/__init__.py
play_audio_with_vlc/requirements.txt
play_audio_with_vlc/thirdparty.json
play_audio_with_vlc-0.10.dist-info/LICENSE.rst
play_audio_with_vlc-0.10.dist-info/METADATA
play_audio_with_vlc-0.10.dist-info/WHEEL
play_audio_with_vlc-0.10.dist-info/top_level.txt
play_audio_with_vlc-0.10.dist-info/RECORD
